{
  "products": [
    {
      "id": 1,
      "name": "상품A",
      "price": 1500000,
      "description": "상품A입니다.",
      "stockQuantity": 50
    },
    {
      "id": 2,
      "name": "상품B",
      "price": 35000,
      "description": "상품B입니다.",
      "stockQuantity": 200
    },
    {
      "id": 3,
      "name": "상품C",
      "price": 120000,
      "description": "상품C입니다.",
      "stockQuantity": 80
    },
    {
      "id": 4,
      "name": "상품D",
      "price": 350000,
      "description": "상품D입니다.",
      "stockQuantity": 30
    }
  ],
  "cartItems": [
    {
      "id": 1,
      "userId": 1,
      "productId": 1,
      "productName": "상품A",
      "price": 1500000,
      "quantity": 1
    },
    {
      "id": 2,
      "userId": 1,
      "productId": 2,
      "productName": "상품B",
      "price": 35000,
      "quantity": 2
    }
  ],
  "orders": [
    {
      "id": 1,
      "userId": 1,
      "orderNumber": "ORDER-1234567890",
      "totalAmount": 1570000,
      "discountAmount": 0,
      "status": "PAID",
      "createdAt": "2025-10-30T10:30:00",
      "items": [
        {
          "productId": 1,
          "productName": "상품A",
          "price": 1500000,
          "quantity": 1
        },
        {
          "productId": 2,
          "productName": "상품B",
          "price": 35000,
          "quantity": 2
        }
      ]
    }
  ],
  "coupons": [
    {
      "id": 1,
      "name": "신규가입할인쿠폰",
      "discountAmount": 10000,
      "availableQuantity": 100,
      "status": "AVAILABLE",
      "expiredAt": "2025-12-31"
    },
    {
      "id": 2,
      "name": "복귀유저할인쿠폰",
      "discountAmount": 50000,
      "availableQuantity": 50,
      "status": "AVAILABLE",
      "expiredAt": "2025-11-30"
    },
    {
      "id": 3,
      "name": "추석할인쿠폰",
      "discountAmount": 100000,
      "availableQuantity": 0,
      "status": "SOLD_OUT",
      "expiredAt": "2025-12-31"
    }
  ],
  "userCoupons": [
    {
      "id": 1,
      "userId": 1,
      "couponId": 1,
      "couponName": "신규가입할인쿠폰",
      "discountAmount": 10000,
      "isUsed": false,
      "usedAt": null,
      "orderId": null,
      "expiredAt": "2025-12-31"
    }
  ],
  "points": [
    {
      "id": 1,
      "userId": 1,
      "balance": 500000
    }
  ],
  "pointTransactions": [
    {
      "id": 1,
      "userId": 1,
      "type": "CHARGE",
      "amount": 500000,
      "balanceAfter": 500000,
      "orderId": null,
      "createdAt": "2025-10-25T14:20:00"
    },
    {
      "id": 2,
      "userId": 1,
      "type": "USE",
      "amount": -1570000,
      "balanceAfter": 500000,
      "orderId": 1,
      "createdAt": "2025-10-30T10:30:00"
    }
  ]
}
